pycyto/__init__.py
pycyto/__main__.py
pycyto/aggregate.py
pycyto/config.py
pycyto/convert.py
pycyto/pipeline.py
pycyto/py.typed
pycyto/vendor/barcodes/737K-fixed-rna-profiling.txt.gz
pycyto/vendor/probe-sets/probe-barcodes-fixed-rna-profiling-ab.txt
pycyto/vendor/probe-sets/probe-barcodes-fixed-rna-profiling-crispr.txt
pycyto/vendor/probe-sets/probe-barcodes-fixed-rna-profiling-rna.txt
pycyto-0.1.13.dist-info/WHEEL
pycyto-0.1.13.dist-info/entry_points.txt
pycyto-0.1.13.dist-info/METADATA
pycyto-0.1.13.dist-info/RECORD
