Metadata-Version: 2.4
Name: pycyto
Version: 0.1.13
Summary: Python utilities used by cyto
Author: Noam Teyssier
Author-email: Noam Teyssier <22600644+noamteyssier@users.noreply.github.com>
License-Expression: MIT
Requires-Dist: anndata>=0.12.2
Requires-Dist: dask>=2025.12.0
Requires-Dist: numpy>=2.3.2
Requires-Dist: pandas>=2.3.1
Requires-Dist: polars>=1.32.3
Requires-Dist: pyarrow>=21.0.0
Requires-Dist: scipy>=1.16.1
Requires-Dist: typer>=0.16.0
Requires-Dist: xarray>=2025.12.0
Requires-Python: >=3.12
